graph_crawler/__init__.py
graph_crawler/__version__.py
graph_crawler/py.typed
graph_crawler/api/__init__.py
graph_crawler/api/_core.py
graph_crawler/api/_distributed.py
graph_crawler/api/_shared.py
graph_crawler/api/_sitemap_distributed.py
graph_crawler/api/async_.py
graph_crawler/api/cli.py
graph_crawler/api/crawl_monitor.py
graph_crawler/api/dashboard.py
graph_crawler/api/history_manager.py
graph_crawler/api/rest_api.py
graph_crawler/api/stats_collector.py
graph_crawler/api/sync.py
graph_crawler/api/webhooks.py
graph_crawler/api/websocket_manager.py
graph_crawler/api/client/__init__.py
graph_crawler/api/client/client.py
graph_crawler/application/__init__.py
graph_crawler/application/context/__init__.py
graph_crawler/application/context/dependency_registry.py
graph_crawler/application/context/graph_context.py
graph_crawler/application/context/merge_context.py
graph_crawler/application/dto/__init__.py
graph_crawler/application/dto/edge_dto.py
graph_crawler/application/dto/graph_dto.py
graph_crawler/application/dto/node_dto.py
graph_crawler/application/dto/utils.py
graph_crawler/application/dto/mappers/__init__.py
graph_crawler/application/dto/mappers/edge_mapper.py
graph_crawler/application/dto/mappers/graph_mapper.py
graph_crawler/application/dto/mappers/node_mapper.py
graph_crawler/application/services/__init__.py
graph_crawler/application/services/application_container.py
graph_crawler/application/services/driver_factory.py
graph_crawler/application/services/storage_factory.py
graph_crawler/application/services/exporters/__init__.py
graph_crawler/application/services/exporters/base_exporter.py
graph_crawler/application/services/exporters/csv_exporter.py
graph_crawler/application/services/exporters/edge_exporter.py
graph_crawler/application/services/exporters/excel_exporter.py
graph_crawler/application/services/exporters/parquet_exporter.py
graph_crawler/application/services/exporters/sql_exporter.py
graph_crawler/application/use_cases/__init__.py
graph_crawler-4.0.3.dist-info/licenses/LICENSE
graph_crawler-4.0.3.dist-info/METADATA
graph_crawler-4.0.3.dist-info/WHEEL
graph_crawler-4.0.3.dist-info/entry_points.txt
graph_crawler-4.0.3.dist-info/top_level.txt
graph_crawler-4.0.3.dist-info/RECORD
