Metadata-Version: 2.4
Name: graph-crawler
Version: 4.0.3
Summary: Sync-First бібліотека для побудови графу веб-сайтів - просто як requests!
Home-page: https://gitlab.com/demoprogrammer/web_graf
Author: 0-EternalJunior-0
Author-email: 
Maintainer: 0-EternalJunior-0
License: MIT
Project-URL: Homepage, https://gitlab.com/demoprogrammer/web_graf
Project-URL: Documentation, https://gitlab.com/demoprogrammer/web_graf/-/blob/main/README.md
Project-URL: Repository, https://gitlab.com/demoprogrammer/web_graf
Project-URL: Bug Tracker, https://gitlab.com/demoprogrammer/web_graf/-/issues
Keywords: web,crawler,scraper,graph,spider,scrapy,vectorization,free-threading
Classifier: Development Status :: 4 - Beta
Classifier: Intended Audience :: Developers
Classifier: Topic :: Software Development :: Libraries :: Python Modules
Classifier: Topic :: Internet :: WWW/HTTP :: Indexing/Search
Classifier: License :: OSI Approved :: MIT License
Classifier: Programming Language :: Python :: 3
Classifier: Programming Language :: Python :: 3.11
Classifier: Programming Language :: Python :: 3.12
Classifier: Programming Language :: Python :: 3.13
Classifier: Programming Language :: Python :: 3.14
Classifier: Operating System :: OS Independent
Requires-Python: >=3.11
License-File: LICENSE
Requires-Dist: requests>=2.31.0
Requires-Dist: beautifulsoup4>=4.12.0
Requires-Dist: lxml>=4.9.0
Requires-Dist: lxml_html_clean
Requires-Dist: pydantic>=2.5.0
Requires-Dist: pydantic-settings>=2.0.0
Requires-Dist: python-dateutil>=2.8.2
Requires-Dist: aiohttp>=3.9.0
Requires-Dist: aiofiles>=23.2.0
Requires-Dist: aiosqlite>=0.19.0
Requires-Dist: selectolax>=0.3.0
Requires-Dist: aiodns>=3.1.0
Requires-Dist: orjson>=3.9.0
Requires-Dist: psutil>=5.9.0
Requires-Dist: pybloom-live
Requires-Dist: fake-useragent
Requires-Dist: dependency-injector
Requires-Dist: fastapi
Requires-Dist: mmh3>=4.0.0
Provides-Extra: playwright
Requires-Dist: playwright>=1.40.0; extra == "playwright"
Provides-Extra: mongodb
Requires-Dist: motor>=3.3.0; extra == "mongodb"
Provides-Extra: postgresql
Requires-Dist: asyncpg>=0.29.0; extra == "postgresql"
Provides-Extra: embeddings
Requires-Dist: sentence-transformers>=2.2.0; extra == "embeddings"
Requires-Dist: numpy>=1.24.0; extra == "embeddings"
Provides-Extra: newspaper
Requires-Dist: newspaper3k>=0.2.8; extra == "newspaper"
Provides-Extra: goose
Requires-Dist: goose3>=3.1.0; extra == "goose"
Provides-Extra: readability
Requires-Dist: readability-lxml>=0.8.0; extra == "readability"
Provides-Extra: articles
Requires-Dist: newspaper3k>=0.2.8; extra == "articles"
Requires-Dist: goose3>=3.1.0; extra == "articles"
Requires-Dist: readability-lxml>=0.8.0; extra == "articles"
Provides-Extra: viz
Requires-Dist: pyvis>=0.3.0; extra == "viz"
Requires-Dist: networkx>=3.6; extra == "viz"
Requires-Dist: plotly>=5.18.0; extra == "viz"
Provides-Extra: celery
Requires-Dist: celery>=5.3.0; extra == "celery"
Requires-Dist: redis>=5.0.0; extra == "celery"
Provides-Extra: dev
Requires-Dist: pytest>=7.4.0; extra == "dev"
Requires-Dist: pytest-asyncio>=0.21.0; extra == "dev"
Requires-Dist: pytest-cov>=4.1.0; extra == "dev"
Requires-Dist: black>=23.0.0; extra == "dev"
Requires-Dist: ruff>=0.1.0; extra == "dev"
Requires-Dist: mypy>=1.5.0; extra == "dev"
Provides-Extra: all
Requires-Dist: playwright>=1.40.0; extra == "all"
Requires-Dist: motor>=3.3.0; extra == "all"
Requires-Dist: asyncpg>=0.29.0; extra == "all"
Requires-Dist: sentence-transformers>=2.2.0; extra == "all"
Requires-Dist: numpy>=1.24.0; extra == "all"
Requires-Dist: newspaper3k>=0.2.8; extra == "all"
Requires-Dist: goose3>=3.1.0; extra == "all"
Requires-Dist: readability-lxml>=0.8.0; extra == "all"
Requires-Dist: pyvis>=0.3.0; extra == "all"
Requires-Dist: networkx>=3.0; extra == "all"
Requires-Dist: plotly>=5.18.0; extra == "all"
Requires-Dist: celery>=5.3.0; extra == "all"
Requires-Dist: redis>=5.0.0; extra == "all"
Dynamic: home-page
Dynamic: license-file
Dynamic: requires-python
